one_qubit/design/lfsr.sv
module lfsr #(
    parameter [14:0] SEED_LFSR =15'h0001
)(
    input logic clk, rst_n,
    output logic [14:0] rand_out
);
    logic feedback;
    assign feedback = rand_out[14] ^ rand_out[0];

    always_ff @(posedge clk, negedge rst_n) begin
        if (!rst_n) begin
            rand_out <= SEED_LFSR;
        end else begin
            // feed_back shift register, use [14, 0] as tap sets
            rand_out <= {feedback, rand_out[14:1]};
        end
    end

endmodule

1_qubit_learn/sv/rtl/single_qubit.sv
module single_qubit (
    input logic clk, rst_n,
    input logic signed [15:0] alpha_real,  // a+bj, value a
    input logic signed [15:0] alpha_imag,  // a+bj, value b
    input logic signed [15:0] beta_real,   // a+bj, value a
    input logic signed [15:0] beta_imag,   // a+bj, value b
    input logic load_en,                   // 0:not loading initial alpha and beta. 1: initial loading. tb will load for 1 clock cycle to read
    input logic measure_en,                // 0:not measuring initial alpha and beta. 1: initial measurement
    input logic [2:0] read_addr,           // address tb wants to read after measurement
    output logic signed [15:0] read_val    // value read after the measurement
);

    logic signed [31:0] P0_val_read;    
    logic signed [31:0] P0_val_imag;
    logic [14:0] P0_val;

    logic [14:0] rand_out;
    lfsr rand_num_gen (
        .clk(clk),
        .rst_n(rst_n),
        .rand_out(rand_out)
    );
    
    // declare the configuration register
    logic signed [15:0] config_mem [4:0];
    assign P0_val_read = config_mem[0] * config_mem[0];
    assign P0_val_imag = config_mem[1] * config_mem[1];
    assign P0_val = P0_val_read[29:15] + P0_val_imag[29:15];
    assign read_val = config_mem[read_addr];


    always_ff @(posedge clk, negedge rst_n) begin
        if (!rst_n) begin
            // clean the memory
            for(int i = 0; i < 5; i++) begin
                config_mem[i] <= '0;
            end
        end else begin
            if (load_en) begin
                config_mem[0] <= alpha_real;
                config_mem[1] <= alpha_imag;
                config_mem[2] <= beta_real;
                config_mem[3] <= beta_imag;
            end 
            // generate random number
            // if random_number < P(0), stores 0. otherwise, store 1
            if (measure_en) begin
                if (rand_out < P0_val) begin
                    config_mem[4] <= 0;
                end else begin
                    config_mem[4] <= 1;
                end
            end
        end 
    end

endmodule

1_qubit_learn/sv/tb/tb_single_qubit.sv
`timescale 1ns/1ps

module tb_single_qubit;

localparam CLK_PERIOD = 10;
localparam NUM_MEASUREMENT = 1000;

logic clk = 0, rst_n;
logic signed [15:0] alpha_real;
logic signed [15:0] alpha_imag;
logic signed [15:0] beta_real;
logic signed [15:0] beta_imag;
logic load_en, measure_en;
logic [2:0] read_addr;
logic signed [15:0] read_val;

real one_chance = 0;
real zero_chance = 0;

// clock generation
always #(CLK_PERIOD / 2) clk = ~clk;

// instantiate the DUT
single_qubit DUT (
    .clk(clk),
    .rst_n(rst_n),
    .alpha_real(alpha_real),
    .alpha_imag(alpha_imag),
    .beta_real(beta_real),
    .beta_imag(beta_imag),
    .load_en(load_en),
    .measure_en(measure_en),
    .read_addr(read_addr),
    .read_val(read_val)
);

// function to reset
task config_reset();
    @(posedge clk);
    rst_n = 0;
    @(posedge clk);
    rst_n = 1;
endtask

task perform_measurement();
    one_chance = 0;
    zero_chance = 0;
    for(int i = 0; i < NUM_MEASUREMENT; i++) begin
        @(posedge clk); 
        load_en = 0;
        measure_en = 1;
        @(posedge clk);
        measure_en = 0;
        read_addr = 4;
        @(posedge clk);
        // if (i < 5) begin
        //     $display("DEBUG: P0_val=%0d, rand_out=%0d, config_mem[0]=%0h",                                                               
        //        DUT.P0_val, DUT.rand_out, DUT.config_mem[0]);                                                                       
        // end  
        if (read_val == 1) begin
            one_chance = one_chance + 1;
        end else begin
            zero_chance = zero_chance + 1;
        end
    end
endtask

// function to assign |0 state
task config_0_state();
    @(posedge clk);
    alpha_real = 16'h7fff;
    alpha_imag = 0;
    beta_real = 0;
    beta_imag = 0;
    load_en = 1;
endtask
// function to assign |1 state
task config_1_state();
    @(posedge clk);
    alpha_real = 0;
    alpha_imag = 0;
    beta_real = 16'h7fff;
    beta_imag = 0;
    load_en = 1;
endtask
// function to assign |+ state
task config_plus_state();
    @(posedge clk);
    alpha_real = 16'h5a82;
    alpha_imag = 0;
    beta_real = 16'h5a82;
    beta_imag = 0;
    load_en = 1;
endtask
// function to assign |- state
task config_minus_state();
    @(posedge clk);
    alpha_real = 16'h5a82;
    alpha_imag = 0;
    beta_real = 16'ha57e;
    beta_imag = 0;
    load_en = 1;
endtask
// function to assign |i state
task config_plus_i_state();
    @(posedge clk);
    alpha_real = 16'h5a82;
    alpha_imag = 0;
    beta_real = 0;
    beta_imag = 16'h5a82;
    load_en = 1;
endtask
// function to assign |-i state
task config_minus_i_state();
    @(posedge clk);
    alpha_real = 16'h5a82;
    alpha_imag = 0;
    beta_real = 0;
    beta_imag = 16'ha57e;
    load_en = 1;
endtask


initial begin
    // reset
    config_reset();
    $display("rst_n=%b", rst_n);
    // |0> state
    config_0_state();
    perform_measurement();
    $display("measured for |0 state. possiblity of getting 0 is %f, getting 1 is %f", zero_chance / (zero_chance + one_chance) , one_chance / (zero_chance + one_chance));
     // |1> state
    config_1_state();
    perform_measurement();
    $display("measured for |1 state. possiblity of getting 0 is %f, getting 1 is %f", zero_chance / (zero_chance + one_chance) , one_chance / (zero_chance + one_chance));
     // |+> state
    config_plus_state();
    perform_measurement();
    $display("measured for |+ state. possiblity of getting 0 is %f, getting 1 is %f", zero_chance / (zero_chance + one_chance) , one_chance / (zero_chance + one_chance));
     // |-> state
    config_minus_state();
    perform_measurement();
    $display("measured for |- state. possiblity of getting 0 is %f, getting 1 is %f", zero_chance / (zero_chance + one_chance) , one_chance / (zero_chance + one_chance));
     // |i> state
    config_plus_i_state();
    perform_measurement();
    $display("measured for |i state. possiblity of getting 0 is %f, getting 1 is %f", zero_chance / (zero_chance + one_chance) , one_chance / (zero_chance + one_chance));
     // |-> state
    config_minus_i_state();
    perform_measurement();
    $display("measured for |-i state. possiblity of getting 0 is %f, getting 1 is %f", zero_chance / (zero_chance + one_chance) , one_chance / (zero_chance + one_chance));
    $finish;
end

// Waveform dump
initial begin
    $dumpfile("qubit_measure_wave.vcd");
    $dumpvars(0, tb_single_qubit);
end

endmodule

1_qubit_learn/sv/qubit_measure_wave.vcd
$date
	Sun Apr  5 23:26:30 2026
$end
$version
	Icarus Verilog
$end
$timescale
	1ps
$end
$scope module tb_single_qubit $end
$var wire 16 ! read_val [15:0] $end
$var parameter 32 " CLK_PERIOD $end
$var parameter 32 # NUM_MEASUREMENT $end
$var reg 16 $ alpha_imag [15:0] $end
$var reg 16 % alpha_real [15:0] $end
$var reg 16 & beta_imag [15:0] $end
$var reg 16 ' beta_real [15:0] $end
$var reg 1 ( clk $end
$var reg 1 ) load_en $end
$var reg 1 * measure_en $end
$var reg 3 + read_addr [2:0] $end
$var reg 1 , rst_n $end
$var real 1 - one_chance $end
$var real 1 . zero_chance $end
$scope module DUT $end
$var wire 16 / alpha_imag [15:0] $end
$var wire 16 0 alpha_real [15:0] $end
$var wire 16 1 beta_imag [15:0] $end
$var wire 16 2 beta_real [15:0] $end
$var wire 1 ( clk $end
$var wire 1 ) load_en $end
$var wire 1 * measure_en $end
$var wire 3 3 read_addr [2:0] $end
$var wire 16 4 read_val [15:0] $end
$var wire 1 , rst_n $end
$var wire 15 5 rand_out [14:0] $end
$var wire 32 6 P0_val_read [31:0] $end
$var wire 32 7 P0_val_imag [31:0] $end
$var wire 15 8 P0_val [14:0] $end
$scope module rand_num_gen $end
$var wire 1 ( clk $end
$var wire 1 9 feedback $end
$var wire 1 , rst_n $end
$var parameter 15 : SEED_LFSR $end
$var reg 15 ; rand_out [14:0] $end
$upscope $end
$scope begin $ivl_for_loop1 $end
$var integer 32 < i [31:0] $end
$upscope $end
$upscope $end
$scope task config_0_state $end
$upscope $end
$scope task config_1_state $end
$upscope $end
$scope task config_minus_i_state $end
$upscope $end
$scope task config_minus_state $end
$upscope $end
$scope task config_plus_i_state $end
$upscope $end
$scope task config_plus_state $end
$upscope $end
$scope task config_reset $end
$upscope $end
$scope task perform_measurement $end
$scope begin $ivl_for_loop0 $end
$var integer 32 = i [31:0] $end
$upscope $end
$upscope $end
$upscope $end
$enddefinitions $end
$comment Show the parameter values. $end
$dumpall
b1 :
b1111101000 #
b1010 "
$end
#0
$dumpvars
b0 =
b0 <
bx ;
x9
bx 8
bx 7
bx 6
bx 5
bx 4
bx 3
bx 2
bx 1
bx 0
bx /
r0 .
r0 -
x,
bx +
x*
x)
0(
bx '
bx &
bx %
bx $
bx !
$end
#5000
19
b0 8
b0 7
b0 6
b1 5
b1 ;
b101 <
0,
1(
#10000
0(
#15000
b100000000000000 5
b100000000000000 ;
1,
1(
#20000
0(
#25000
b111111111111110 8
b111111111111110000000000000001 6
b110000000000000 5
b110000000000000 ;
1)
b0 &
b0 1
b0 '
b0 2
b0 $
b0 /
b111111111111111 %
b111111111111111 0
1(
#30000
0(
#35000
b111000000000000 5
b111000000000000 ;
1*
0)
1(
#40000
0(
#45000
b111100000000000 5
b111100000000000 ;
b0 !
b0 4
b100 +
b100 3
0*
1(
#50000
0(
#55000
b111110000000000 5
b111110000000000 ;
b1 =
r1 .
1(
#60000
0(
#65000
b111111000000000 5
b111111000000000 ;
1*
1(
#70000
0(
#75000
b111111100000000 5
b111111100000000 ;
0*
1(
#80000
0(
#85000
b111111110000000 5
b111111110000000 ;
b10 =
r2 .
1(
#90000
0(
#95000
b111111111000000 5
b111111111000000 ;
1*
1(
#100000
0(
#105000
b111111111100000 5
b111111111100000 ;
0*
1(
#110000
0(
#115000
b111111111110000 5
b111111111110000 ;
b11 =
r3 .
1(
#120000
0(
#125000
b111111111111000 5
b111111111111000 ;
1*
1(
#130000
0(
#135000
b111111111111100 5
b111111111111100 ;
0*
1(
#140000
0(
#145000
b111111111111110 5
b111111111111110 ;
b100 =
r4 .
1(
#150000
0(
#155000
09
b111111111111111 5
b111111111111111 ;
b1 !
b1 4
1*
1(
#160000
0(
#165000
19
b11111111111111 5
b11111111111111 ;
0*
1(
#170000
0(
#175000
09
b101111111111111 5
b101111111111111 ;
b101 =
r1 -
1(
#180000
0(
#185000
19
b0 !
b0 4
b10111111111111 5
b10111111111111 ;
1*
1(
#190000
0(
#195000
09
b101011111111111 5
b101011111111111 ;
0*
1(
#200000
0(
#205000
19
b10101111111111 5
b10101111111111 ;
b110 =
r5 .
1(
#210000
0(
#215000
09
b101010111111111 5
b101010111111111 ;
1*
1(
#220000
0(
#225000
19
b10101011111111 5
b10101011111111 ;
0*
1(
#230000
0(
#235000
09
b101010101111111 5
b101010101111111 ;
b111 =
r6 .
1(
#240000
0(
#245000
19
b10101010111111 5
b10101010111111 ;
1*
1(
#250000
0(
#255000
09
b101010101011111 5
b101010101011111 ;
0*
1(
#260000
0(
#265000
19
b10101010101111 5
b10101010101111 ;
b1000 =
r7 .
1(
#270000
0(
#275000
09
b101010101010111 5
b101010101010111 ;
1*
1(
#280000
0(
#285000
19
b10101010101011 5
b10101010101011 ;
0*
1(
#290000
0(
#295000
09
b101010101010101 5
b101010101010101 ;
b1001 =
r8 .
1(
#300000
0(
#305000
b10101010101010 5
b10101010101010 ;
1*
1(
#310000
0(
#315000
19
b1010101010101 5
b1010101010101 ;
0*
1(
#320000
0(
#325000
b100101010101010 5
b100101010101010 ;
b1010 =
r9 .
1(
#330000
0(
#335000
09
b110010101010101 5
b110010101010101 ;
1*
1(
#340000
0(
#345000
b11001010101010 5
b11001010101010 ;
0*
1(
#350000
0(
#355000
19
b1100101010101 5
b1100101010101 ;
b1011 =
r10 .
1(
#360000
0(
#365000
b100110010101010 5
b100110010101010 ;
1*
1(
#370000
0(
#375000
09
b110011001010101 5
b110011001010101 ;
0*
1(
#380000
0(
#385000
b11001100101010 5
b11001100101010 ;
b1100 =
r11 .
1(
#390000
0(
#395000
19
b1100110010101 5
b1100110010101 ;
1*
1(
#400000
0(
#405000
b100110011001010 5
b100110011001010 ;
0*
1(
#410000
0(
#415000
09
b110011001100101 5
b110011001100101 ;
b1101 =
r12 .
1(
#420000
0(
#425000
b11001100110010 5
b11001100110010 ;
1*
1(
#430000
0(
#435000
19
b1100110011001 5
b1100110011001 ;
0*
1(
#440000
0(
#445000
b100110011001100 5
b100110011001100 ;
b1110 =
r13 .
1(
#450000
0(
#455000
b110011001100110 5
b110011001100110 ;
1*
1(
#460000
0(
#465000
09
b111001100110011 5
b111001100110011 ;
0*
1(
#470000
0(
#475000
19
b11100110011001 5
b11100110011001 ;
b1111 =
r14 .
1(
#480000
0(
#485000
b101110011001100 5
b101110011001100 ;
1*
1(
#490000
0(
#495000
b110111001100110 5
b110111001100110 ;
0*
1(
#500000
0(
#505000
09
b111011100110011 5
b111011100110011 ;
b10000 =
r15 .
1(
#510000
0(
#515000
19
b11101110011001 5
b11101110011001 ;
1*
1(
#520000
0(
#525000
b101110111001100 5
b101110111001100 ;
0*
1(
#530000
0(
#535000
b110111011100110 5
b110111011100110 ;
b10001 =
r16 .
1(
#540000
0(
#545000
09
b111011101110011 5
b111011101110011 ;
1*
1(
#550000
0(
#555000
19
b11101110111001 5
b11101110111001 ;
0*
1(
#560000
0(
#565000
b101110111011100 5
b101110111011100 ;
b10010 =
r17 .
1(
#570000
0(
#575000
b110111011101110 5
b110111011101110 ;
1*
1(
#580000
0(
#585000
09
b111011101110111 5
b111011101110111 ;
0*
1(
#590000
0(
#595000
19
b11101110111011 5
b11101110111011 ;
b10011 =
r18 .
1(
#600000
0(
#605000
09
b101110111011101 5
b101110111011101 ;
1*
1(
#610000
0(
#615000
b10111011101110 5
b10111011101110 ;
0*
1(
#620000
0(
#625000
19
b1011101110111 5
b1011101110111 ;
b10100 =
r19 .
1(
#630000
0(
#635000
09
b100101110111011 5
b100101110111011 ;
1*
1(
#640000
0(
#645000
19
b10010111011101 5
b10010111011101 ;
0*
1(
#650000
0(
#655000
b101001011101110 5
b101001011101110 ;
b10101 =
r20 .
1(
#660000
0(
#665000
09
b110100101110111 5
b110100101110111 ;
1*
1(
#670000
0(
#675000
19
b11010010111011 5
b11010010111011 ;
0*
1(
#680000
0(
#685000
09
b101101001011101 5
b101101001011101 ;
b10110 =
r21 .
1(
#690000
0(
#695000
b10110100101110 5
b10110100101110 ;
1*
1(
#700000
0(
#705000
19
b1011010010111 5
b1011010010111 ;
0*
1(
#710000
0(
#715000
09
b100101101001011 5
b100101101001011 ;
b10111 =
r22 .
1(
#720000
0(
#725000
19
b10010110100101 5
b10010110100101 ;
1*
1(
#730000
0(
#735000
b101001011010010 5
b101001011010010 ;
0*
1(
#740000
0(
#745000
09
b110100101101001 5
b110100101101001 ;
b11000 =
r23 .
1(
#750000
0(
#755000
b11010010110100 5
b11010010110100 ;
1*
1(
#760000
0(
#765000
b1101001011010 5
b1101001011010 ;
0*
1(
#770000
0(
#775000
19
b110100101101 5
b110100101101 ;
b11001 =
r24 .
1(
#780000
0(
#785000
b100011010010110 5
b100011010010110 ;
1*
1(
#790000
0(
#795000
09
b110001101001011 5
b110001101001011 ;
0*
1(
#800000
0(
#805000
19
b11000110100101 5
b11000110100101 ;
b11010 =
r25 .
1(
#810000
0(
#815000
b101100011010010 5
b101100011010010 ;
1*
1(
#820000
0(
#825000
09
b110110001101001 5
b110110001101001 ;
0*
1(
#830000
0(
#835000
b11011000110100 5
b11011000110100 ;
b11011 =
r26 .
1(
#840000
0(
#845000
b1101100011010 5
b1101100011010 ;
1*
1(
#850000
0(
#855000
19
b110110001101 5
b110110001101 ;
0*
1(
#860000
0(
#865000
b100011011000110 5
b100011011000110 ;
b11100 =
r27 .
1(
#870000
0(
#875000
09
b110001101100011 5
b110001101100011 ;
1*
1(
#880000
0(
#885000
19
b11000110110001 5
b11000110110001 ;
0*
1(
#890000
0(
#895000
b101100011011000 5
b101100011011000 ;
b11101 =
r28 .
1(
#900000
0(
#905000
b110110001101100 5
b110110001101100 ;
1*
1(
#910000
0(
#915000
b111011000110110 5
b111011000110110 ;
0*
1(
#920000
0(
#925000
09
b111101100011011 5
b111101100011011 ;
b11110 =
r29 .
1(
#930000
0(
#935000
19
b11110110001101 5
b11110110001101 ;
1*
1(
#940000
0(
#945000
b101111011000110 5
b101111011000110 ;
0*
1(
#950000
0(
#955000
09
b110111101100011 5
b110111101100011 ;
b11111 =
r30 .
1(
#960000
0(
#965000
19
b11011110110001 5
b11011110110001 ;
1*
1(
#970000
0(
#975000
b101101111011000 5
b101101111011000 ;
0*
1(
#980000
0(
#985000
b110110111101100 5
b110110111101100 ;
b100000 =
r31 .
1(
#990000
0(
#995000
b111011011110110 5
b111011011110110 ;
1*
1(
#1000000
0(
#1005000
09
b111101101111011 5
b111101101111011 ;
0*
1(
#1010000
0(
#1015000
19
b11110110111101 5
b11110110111101 ;
b100001 =
r32 .
1(
#1020000
0(
#1025000
b101111011011110 5
b101111011011110 ;
1*
1(
#1030000
0(
#1035000
09
b110111101101111 5
b110111101101111 ;
0*
1(
#1040000
0(
#1045000
19
b11011110110111 5
b11011110110111 ;
b100010 =
r33 .
1(
#1050000
0(
#1055000
09
b101101111011011 5
b101101111011011 ;
1*
1(
#1060000
0(
#1065000
19
b10110111101101 5
b10110111101101 ;
0*
1(
#1070000
0(
#1075000
b101011011110110 5
b101011011110110 ;
b100011 =
r34 .
1(
#1080000
0(
#1085000
09
b110101101111011 5
b110101101111011 ;
1*
1(
#1090000
0(
#1095000
19
b11010110111101 5
b11010110111101 ;
0*
1(
#1100000
0(
#1105000
b101101011011110 5
b101101011011110 ;
b100100 =
r35 .
1(
#1110000
0(
#1115000
09
b110110101101111 5
b110110101101111 ;
1*
1(
#1120000
0(
#1125000
19
b11011010110111 5
b11011010110111 ;
0*
1(
#1130000
0(
#1135000
09
b101101101011011 5
b101101101011011 ;
b100101 =
r36 .
1(
#1140000
0(
#1145000
19
b10110110101101 5
b10110110101101 ;
1*
1(
#1150000
0(
#1155000
b101011011010110 5
b101011011010110 ;
0*
1(
#1160000
0(
#1165000
09
b110101101101011 5
b110101101101011 ;
b100110 =
r37 .
1(
#1170000
0(
#1175000
19
b11010110110101 5
b11010110110101 ;
1*
1(
#1180000
0(
#1185000
b101101011011010 5
b101101011011010 ;
0*
1(
#1190000
0(
#1195000
09
b110110101101101 5
b110110101101101 ;
b100111 =
r38 .
1(
#1200000
0(
#1205000
b11011010110110 5
b11011010110110 ;
1*
1(
#1210000
0(
#1215000
19
b1101101011011 5
b1101101011011 ;
0*
1(
#1220000
0(
#1225000
09
b100110110101101 5
b100110110101101 ;
b101000 =
r39 .
1(
#1230000
0(
#1235000
b10011011010110 5
b10011011010110 ;
1*
1(
#1240000
0(
#1245000
19
b1001101101011 5
b1001101101011 ;
0*
1(
#1250000
0(
#1255000
09
b100100110110101 5
b100100110110101 ;
b101001 =
r40 .
1(
#1260000
0(
#1265000
b10010011011010 5
b10010011011010 ;
1*
1(
#1270000
0(
#1275000
19
b1001001101101 5
b1001001101101 ;
0*
1(
#1280000
0(
#1285000
b100100100110110 5
b100100100110110 ;
b101010 =
r41 .
1(
#1290000
0(
#1295000
09
b110010010011011 5
b110010010011011 ;
1*
1(
#1300000
0(
#1305000
19
b11001001001101 5
b11001001001101 ;
0*
1(
#1310000
0(
#1315000
b101100100100110 5
b101100100100110 ;
b101011 =
r42 .
1(
#1320000
0(
#1325000
09
b110110010010011 5
b110110010010011 ;
1*
1(
#1330000
0(
#1335000
19
b11011001001001 5
b11011001001001 ;
0*
1(
#1340000
0(
#1345000
b101101100100100 5
b101101100100100 ;
b101100 =
r43 .
1(
#1350000
0(
#1355000
b110110110010010 5
b110110110010010 ;
1*
1(
#1360000
0(
#1365000
09
b111011011001001 5
b111011011001001 ;
0*
1(
#1370000
0(
#1375000
b11101101100100 5
b11101101100100 ;
b101101 =
r44 .
1(
#1380000
0(
#1385000
b1110110110010 5
b1110110110010 ;
1*
1(
#1390000
0(
#1395000
19
b111011011001 5
b111011011001 ;
0*
1(
#1400000
0(
#1405000
b100011101101100 5
b100011101101100 ;
b101110 =
r45 .
1(
#1410000
0(
#1415000
b110001110110110 5
b110001110110110 ;
1*
1(
#1420000
0(
#1425000
09
b111000111011011 5
b111000111011011 ;
0*
1(
#1430000
0(
#1435000
19
b11100011101101 5
b11100011101101 ;
b101111 =
r46 .
1(
#1440000
0(
#1445000
b101110001110110 5
b101110001110110 ;
1*
1(
#1450000
0(
#1455000
09
b110111000111011 5
b110111000111011 ;
0*
1(
#1460000
0(
#1465000
19
b11011100011101 5
b11011100011101 ;
b110000 =
r47 .
1(
#1470000
0(
#1475000
b101101110001110 5
b101101110001110 ;
1*
1(
#1480000
0(
#1485000
09
b110110111000111 5
b110110111000111 ;
0*
1(
#1490000
0(
#1495000
19
b11011011100011 5
b11011011100011 ;
b110001 =
r48 .
1(
#1500000
0(
#1505000
09
b101101101110001 5
b101101101110001 ;
1*
1(
#1510000
0(
#1515000
b10110110111000 5
b10110110111000 ;
0*
1(
#1520000
0(
#1525000
b1011011011100 5
b1011011011100 ;
b110010 =
r49 .
1(
#1530000
0(
#1535000
b101101101110 5
b101101101110 ;
1*
1(
#1540000
0(
#1545000
19
b10110110111 5
b10110110111 ;
0*
1(
#1550000
0(
#1555000
09
b100001011011011 5
b100001011011011 ;
b110011 =
r50 .
1(
#1560000
0(
#1565000
19
b10000101101101 5
b10000101101101 ;
1*
1(
#1570000
0(
#1575000
b101000010110110 5
b101000010110110 ;
0*
1(
#1580000
0(
#1585000
09
b110100001011011 5
b110100001011011 ;
b110100 =
r51 .
1(
#1590000
0(
#1595000
19
b11010000101101 5
b11010000101101 ;
1*
1(
#1600000
0(
#1605000
b101101000010110 5
b101101000010110 ;
0*
1(
#1610000
0(
#1615000
09
b110110100001011 5
b110110100001011 ;
b110101 =
r52 .
1(
#1620000
0(
#1625000
19
b11011010000101 5
b11011010000101 ;
1*
1(
#1630000
0(
#1635000
b101101101000010 5
b101101101000010 ;
0*
1(
#1640000
0(
#1645000
09
b110110110100001 5
b110110110100001 ;
b110110 =
r53 .
1(
#1650000
0(
#1655000
b11011011010000 5
b11011011010000 ;
1*
1(
#1660000
0(
#1665000
b1101101101000 5
b1101101101000 ;
0*
1(
#1670000
0(
#1675000
b110110110100 5
b110110110100 ;
b110111 =
r54 .
1(
#1680000
0(
#1685000
b11011011010 5
b11011011010 ;
1*
1(
#1690000
0(
#1695000
19
b1101101101 5
b1101101101 ;
0*
1(
#1700000
0(
#1705000
b100000110110110 5
b100000110110110 ;
b111000 =
r55 .
1(
#1710000
0(
#1715000
09
b110000011011011 5
b110000011011011 ;
1*
1(
#1720000
0(
#1725000
19
b11000001101101 5
b11000001101101 ;
0*
1(
#1730000
0(
#1735000
b101100000110110 5
b101100000110110 ;
b111001 =
r56 .
1(
#1740000
0(
#1745000
09
b110110000011011 5
b110110000011011 ;
1*
1(
#1750000
0(
#1755000
19
b11011000001101 5
b11011000001101 ;
0*
1(
#1760000
0(
#1765000
b101101100000110 5
b101101100000110 ;
b111010 =
r57 .
1(
#1770000
0(
#1775000
09
b110110110000011 5
b110110110000011 ;
1*
1(
#1780000
0(
#1785000
19
b11011011000001 5
b11011011000001 ;
0*
1(
#1790000
0(
#1795000
b101101101100000 5
b101101101100000 ;
b111011 =
r58 .
1(
#1800000
0(
#1805000
b110110110110000 5
b110110110110000 ;
1*
1(
#1810000
0(
#1815000
b111011011011000 5
b111011011011000 ;
0*
1(
#1820000
0(
#1825000
b111101101101100 5
b111101101101100 ;
b111100 =
r59 .
1(
#1830000
0(
#1835000
b111110110110110 5
b111110110110110 ;
1*
1(
#1840000
0(
#1845000
09
b111111011011011 5
b111111011011011 ;
0*
1(
#1850000
0(
#1855000
19
b11111101101101 5
b11111101101101 ;
b111101 =
r60 .
1(
#1860000
0(
#1865000
b101111110110110 5
b101111110110110 ;
1*
1(
#1870000
0(
#1875000
09
b110111111011011 5
b110111111011011 ;
0*
1(
#1880000
0(
#1885000
19
b11011111101101 5
b11011111101101 ;
b111110 =
r61 .
1(
#1890000
0(
#1895000
b101101111110110 5
b101101111110110 ;
1*
1(
#1900000
0(
#1905000
09
b110110111111011 5
b110110111111011 ;
0*
1(
#1910000
0(
#1915000
19
b11011011111101 5
b11011011111101 ;
b111111 =
r62 .
1(
#1920000
0(
#1925000
b101101101111110 5
b101101101111110 ;
1*
1(
#1930000
0(
#1935000
09
b110110110111111 5
b110110110111111 ;
0*
1(
#1940000
0(
#1945000
19
b11011011011111 5
b11011011011111 ;
b1000000 =
r63 .
1(
#1950000
0(
#1955000
09
b101101101101111 5
b101101101101111 ;
1*
1(
#1960000
0(
#1965000
19
b10110110110111 5
b10110110110111 ;
0*
1(
#1970000
0(
#1975000
09
b101011011011011 5
b101011011011011 ;
b1000001 =
r64 .
1(
#1980000
0(
#1985000
19
b10101101101101 5
b10101101101101 ;
1*
1(
#1990000
0(
#1995000
b101010110110110 5
b101010110110110 ;
0*
1(
#2000000
0(
#2005000
09
b110101011011011 5
b110101011011011 ;
b1000010 =
r65 .
1(
#2010000
0(
#2015000
19
b11010101101101 5
b11010101101101 ;
1*
1(
#2020000
0(
#2025000
b101101010110110 5
b101101010110110 ;
0*
1(
#2030000
0(
#2035000
09
b110110101011011 5
b110110101011011 ;
b1000011 =
r66 .
1(
#2040000
0(
#2045000
19
b11011010101101 5
b11011010101101 ;
1*
1(
#2050000
0(
#2055000
b101101101010110 5
b101101101010110 ;
0*
1(
#2060000
0(
#2065000
09
b110110110101011 5
b110110110101011 ;
b1000100 =
r67 .
1(
#2070000
0(
#2075000
19
b11011011010101 5
b11011011010101 ;
1*
1(
#2080000
0(
#2085000
b101101101101010 5
b101101101101010 ;
0*
1(
#2090000
0(
#2095000
09
b110110110110101 5
b110110110110101 ;
b1000101 =
r68 .
1(
#2100000
0(
#2105000
b11011011011010 5
b11011011011010 ;
1*
1(
#2110000
0(
#2115000
19
b1101101101101 5
b1101101101101 ;
0*
1(
#2120000
0(
#2125000
b100110110110110 5
b100110110110110 ;
b1000110 =
r69 .
1(
#2130000
0(
#2135000
09
b110011011011011 5
b110011011011011 ;
1*
1(
#2140000
0(
#2145000
19
b11001101101101 5
b11001101101101 ;
0*
1(
#2150000
0(
#2155000
b101100110110110 5
b101100110110110 ;
b1000111 =
r70 .
1(
#2160000
0(
#2165000
09
b110110011011011 5
b110110011011011 ;
1*
1(
#2170000
0(
#2175000
19
b11011001101101 5
b11011001101101 ;
0*
1(
#2180000
0(
#2185000
b101101100110110 5
b101101100110110 ;
b1001000 =
r71 .
1(
#2190000
0(
#2195000
09
b110110110011011 5
b110110110011011 ;
1*
1(
#2200000
0(
#2205000
19
b11011011001101 5
b11011011001101 ;
0*
1(
#2210000
0(
#2215000
b101101101100110 5
b101101101100110 ;
b1001001 =
r72 .
1(
#2220000
0(
#2225000
09
b110110110110011 5
b110110110110011 ;
1*
1(
#2230000
0(
#2235000
19
b11011011011001 5
b11011011011001 ;
0*
1(
#2240000
0(
#2245000
b101101101101100 5
b101101101101100 ;
b1001010 =
r73 .
1(
#2250000
0(
#2255000
b110110110110110 5
b110110110110110 ;
1*
1(
#2260000
0(
#2265000
09
b111011011011011 5
b111011011011011 ;
0*
1(
#2270000
0(
#2275000
19
b11101101101101 5
b11101101101101 ;
b1001011 =
r74 .
1(
#2280000
0(
#2285000
b101110110110110 5
b101110110110110 ;
1*
1(
#2290000
0(
#2295000
09
b110111011011011 5
b110111011011011 ;
0*
1(
#2300000
0(
#2305000
19
b11011101101101 5
b11011101101101 ;
b1001100 =
r75 .
1(
#2310000
0(
#2315000
b101101110110110 5
b101101110110110 ;
1*
1(
#2320000
0(
#2325000
09
b110110111011011 5
b110110111011011 ;
0*
1(
#2330000
0(
#2335000
19
b11011011101101 5
b11011011101101 ;
b1001101 =
r76 .
1(
#2340000
0(
#2345000
b101101101110110 5
b101101101110110 ;
1*
1(
#2350000
0(
#2355000
09
b110110110111011 5
b110110110111011 ;
0*
1(
#2360000
0(
#2365000
19
b11011011011101 5
b11011011011101 ;
b1001110 =
r77 .
1(
#2370000
0(
#2375000
b101101101101110 5
b101101101101110 ;
1*
1(
#2380000
0(
#2385000
09
b110110110110111 5
b110110110110111 ;
0*
1(
#2390000
0(
#2395000
19
b11011011011011 5
b11011011011011 ;
b1001111 =
r78 .
1(
#2400000
0(
#2405000
09
b101101101101101 5
b101101101101101 ;
1*
1(
#2410000
0(
#2415000
b10110110110110 5
b10110110110110 ;
0*
1(
#2420000
0(
#2425000
19
b1011011011011 5
b1011011011011 ;
b1010000 =
r79 .
1(
#2430000
0(
#2435000
09
b100101101101101 5
b100101101101101 ;
1*
1(
#2440000
0(
#2445000
b10010110110110 5
b10010110110110 ;
0*
1(
#2450000
0(
#2455000
19
b1001011011011 5
b1001011011011 ;
b1010001 =
r80 .
1(
#2460000
0(
#2465000
09
b100100101101101 5
b100100101101101 ;
1*
1(
#2470000
0(
#2475000
b10010010110110 5
b10010010110110 ;
0*
1(
#2480000
0(
#2485000
19
b1001001011011 5
b1001001011011 ;
b1010010 =
r81 .
1(
#2490000
0(
#2495000
09
b100100100101101 5
b100100100101101 ;
1*
1(
#2500000
0(
#2505000
b10010010010110 5
b10010010010110 ;
0*
1(
#2510000
0(
#2515000
19
b1001001001011 5
b1001001001011 ;
b1010011 =
r82 .
1(
#2520000
0(
#2525000
09
b100100100100101 5
b100100100100101 ;
1*
1(
#2530000
0(
#2535000
b10010010010010 5
b10010010010010 ;
0*
1(
#2540000
0(
#2545000
19
b1001001001001 5
b1001001001001 ;
b1010100 =
r83 .
1(
#2550000
0(
#2555000
b100100100100100 5
b100100100100100 ;
1*
1(
#2560000
0(
#2565000
b110010010010010 5
b110010010010010 ;
0*
1(
#2570000
0(
#2575000
09
b111001001001001 5
b111001001001001 ;
b1010101 =
r84 .
1(
#2580000
0(
#2585000
b11100100100100 5
b11100100100100 ;
1*
1(
